django_schedule_frinat-0.6.dist-info/DESCRIPTION.rst
django_schedule_frinat-0.6.dist-info/METADATA
django_schedule_frinat-0.6.dist-info/pydist.json
django_schedule_frinat-0.6.dist-info/RECORD
django_schedule_frinat-0.6.dist-info/top_level.txt
django_schedule_frinat-0.6.dist-info/WHEEL
schedule/__init__.py
schedule/admin.py
schedule/forms.py
schedule/periods.py
schedule/signals.py
schedule/urls.py
schedule/utils.py
schedule/views.py
schedule/conf/__init__.py
schedule/conf/settings.py
schedule/feeds/__init__.py
schedule/feeds/atom.py
schedule/feeds/icalendar.py
schedule/management/__init__.py
schedule/management/commands/__init__.py
schedule/management/commands/load_example_data.py
schedule/management/commands/load_sample_data.py
schedule/models/__init__.py
schedule/models/calendars.py
schedule/models/events.py
schedule/models/rules.py
schedule/templates/profiles/schedule.html
schedule/templates/schedule/_create_event_options.html
schedule/templates/schedule/_daily_table.html
schedule/templates/schedule/_day_cell.html
schedule/templates/schedule/_detail.html
schedule/templates/schedule/_dialogs.html
schedule/templates/schedule/_event_options.html
schedule/templates/schedule/_event_title.html
schedule/templates/schedule/_month_table.html
schedule/templates/schedule/_prevnext.html
schedule/templates/schedule/base.html
schedule/templates/schedule/calendar.html
schedule/templates/schedule/calendar_compact_month.html
schedule/templates/schedule/calendar_day.html
schedule/templates/schedule/calendar_list.html
schedule/templates/schedule/calendar_month.html
schedule/templates/schedule/calendar_tri_month.html
schedule/templates/schedule/calendar_week.html
schedule/templates/schedule/calendar_year.html
schedule/templates/schedule/cancel_occurrence.html
schedule/templates/schedule/create_event.html
schedule/templates/schedule/delete_event.html
schedule/templates/schedule/edit_occurrence.html
schedule/templates/schedule/event.html
schedule/templates/schedule/event_form_base.html
schedule/templates/schedule/occurrence.html
schedule/templatetags/__init__.py
schedule/templatetags/scheduletags.py
schedule/tests/__init__.py
schedule/tests/test_models.py
schedule/tests/test_periods.py
schedule/tests/test_rule.py
