Metadata-Version: 2.0
Name: django-schedule-frinat
Version: 0.6
Summary: A calendaring app for Django (frinat edition).
Home-page: http://github.com/thauber/django-schedule/tree/master
Author: Anthony Robert Hauber
Author-email: thauber@gmail.com
License: BSD
Platform: UNKNOWN
Classifier: Development Status :: 4 - Beta
Classifier: Environment :: Web Environment
Classifier: Framework :: Django
Classifier: Intended Audience :: Developers
Classifier: License :: OSI Approved :: BSD License
Classifier: Operating System :: OS Independent
Classifier: Programming Language :: Python
Classifier: Topic :: Utilities
Requires-Dist: setuptools
Requires-Dist: vobject
Requires-Dist: python-dateutil (==1.5)
